Workbook

Sheet Assumptions
A1: NVIDIA (NVDA) Discounted Cash Flow Model
A3: WACC Assumptions
A4: Risk-free rate | B4: 0.04
A5: Beta | B5: 2.27
A6: Equity risk premium | B6: 0.05
A7: Cost of debt (pre-tax) | B7: 0.03
A8: Tax rate | B8: 0.15
A9: Equity weight | B9: 0.95
A10: Debt weight | B10: 0.05
A11: Cost of equity | B11: =B4 + B5*B6 -> 0.1535
A12: Cost of debt (after tax) | B12: =B7*(1 - B8) -> 0.0255
A13: WACC | B13: =B9*B11 + B10*B12 -> 0.1471
A15: Forecast Assumptions
A16: Base year revenue (FY2025, m) | B16: 130497
A17: Year | B17: 2026 | C17: 2027 | D17: 2028 | E17: 2029 | F17: 2030
A18: Revenue growth | B18: 0.5 | C18: 0.3 | D18: 0.2 | E18: 0.1 | F18: 0.05
A19: EBIT margin | B19: 0.6 | C19: 0.55 | D19: 0.5 | E19: 0.45 | F19: 0.4
A20: D&A ratio | B20: 0.013 | C20: 0.012 | D20: 0.011 | E20: 0.01 | F20: 0.009
A21: CapEx ratio | B21: 0.03 | C21: 0.03 | D21: 0.035 | E21: 0.035 | F21: 0.04
A22: Working capital ratio | B22: -0.07 | C22: -0.07 | D22: -0.07 | E22: -0.07 | F22: -0.07
A24: Terminal assumptions
A25: Terminal growth rate | B25: 0.03
A26: Exit EBITDA multiple (base) | B26: 35
A28: Net cash (m) | B28: 52133
A29: Shares outstanding (m) | B29: 24305

Sheet Historical Data
A1: Historical Financial Data
A3: Year | B3: Revenue (m) | C3: EBIT (m) | D3: D&A (m) | E3: CapEx (m) | F3: WC change (m) | G3: NOPAT (m) | H3: FCF (m) | I3: EBIT Margin | J3: D&A/Rev | K3: CapEx/Rev | L3: WC/Rev
A4: FY2023 | B4: 26974 | C4: 4224 | D4: 1544 | E4: 1833 | F4: -2459 | G4: =C4*(1 - Assumptions!$B$8) -> 3590.4 | H4: =G4 + D4 - E4 - F4 -> 5760.4 | I4: =C4/B4 -> 0.15659524 | J4: =D4/B4 -> 0.057240305 | K4: =E4/B4 -> 0.067954326 | L4: =F4/B4 -> -0.09116186
A5: FY2024 | B5: 60922 | C5: 32972 | D5: 1508 | E5: 1069 | F5: -4236 | G5: =C5*(1 - Assumptions!$B$8) -> 28026.2 | H5: =G5 + D5 - E5 - F5 -> 32701.2 | I5: =C5/B5 -> 0.54121664 | J5: =D5/B5 -> 0.024752963 | K5: =E5/B5 -> 0.017547027 | L5: =F5/B5 -> -0.069531532
A6: FY2025 | B6: 130497 | C6: 81453 | D6: 1864 | E6: 3236 | F6: -10604 | G6: =C6*(1 - Assumptions!$B$8) -> 69235.05 | H6: =G6 + D6 - E6 - F6 -> 78467.05 | I6: =C6/B6 -> 0.62417527 | J6: =D6/B6 -> 0.014283853 | K6: =E6/B6 -> 0.024797505 | L6: =F6/B6 -> -0.081258573

Sheet Projections
A1: Financial Projections
A3: Year
A4: Revenue (m) | B4: =Assumptions!B16*(1+Assumptions!B18) -> 195745.5 | C4: =B4*(1+Assumptions!C18) -> 254469.15 | D4: =C4*(1+Assumptions!D18) -> 305362.98 | E4: =D4*(1+Assumptions!E18) -> 335899.28 | F4: =E4*(1+Assumptions!F18) -> 352694.24
A5: EBIT (m) | B5: =B4*Assumptions!B19 -> 117447.3 | C5: =C4*Assumptions!C19 -> 139958.03 | D5: =D4*Assumptions!D19 -> 152681.49 | E5: =E4*Assumptions!E19 -> 151154.68 | F5: =F4*Assumptions!F19 -> 141077.7
A6: D&A (m) | B6: =B4*Assumptions!B20 -> 2544.6915 | C6: =C4*Assumptions!C20 -> 3053.6298 | D6: =D4*Assumptions!D20 -> 3358.9928 | E6: =E4*Assumptions!E20 -> 3358.9928 | F6: =F4*Assumptions!F20 -> 3174.2482
A7: CapEx (m) | B7: =B4*Assumptions!B21 -> 5872.365 | C7: =C4*Assumptions!C21 -> 7634.0745 | D7: =D4*Assumptions!D21 -> 10687.704 | E7: =E4*Assumptions!E21 -> 11756.475 | F7: =F4*Assumptions!F21 -> 14107.77
A8: WC change (m) | B8: =B4*Assumptions!B22 -> -13702.185 | C8: =C4*Assumptions!C22 -> -17812.841 | D8: =D4*Assumptions!D22 -> -21375.409 | E8: =E4*Assumptions!E22 -> -23512.949 | F8: =F4*Assumptions!F22 -> -24688.597
A9: NOPAT (m) | B9: =B5*(1 - Assumptions!$B$8) -> 99830.205 | C9: =C5*(1 - Assumptions!$B$8) -> 118964.33 | D9: =D5*(1 - Assumptions!$B$8) -> 129779.27 | E9: =E5*(1 - Assumptions!$B$8) -> 128481.47 | F9: =F5*(1 - Assumptions!$B$8) -> 119916.04
A10: Free cash flow (m) | B10: =B9 + B6 - B7 - B8 -> 110204.72 | C10: =C9 + C6 - C7 - C8 -> 132196.72 | D10: =D9 + D6 - D7 - D8 -> 143825.96 | E10: =E9 + E6 - E7 - E8 -> 143596.94 | F10: =F9 + F6 - F7 - F8 -> 133671.12
A11: EBITDA (m) | B11: =B5 + B6 -> 119991.99 | C11: =C5 + C6 -> 143011.66 | D11: =D5 + D6 -> 156040.48 | E11: =E5 + E6 -> 154513.67 | F11: =F5 + F6 -> 144251.94

Sheet DCF
A1: DCF Valuation
A4: FCF (m) | B4: =Projections!B10 -> 110204.72 | C4: =Projections!C10 -> 132196.72 | D4: =Projections!D10 -> 143825.96 | E4: =Projections!E10 -> 143596.94 | F4: =Projections!F10 -> 133671.12
A5: Discount factor | B5: =1/(1+Assumptions!$B$13)^1 -> 0.87176358 | C5: =1/(1+Assumptions!$B$13)^2 -> 0.75997174 | D5: =1/(1+Assumptions!$B$13)^3 -> 0.66251568 | E5: =1/(1+Assumptions!$B$13)^4 -> 0.57755704 | F5: =1/(1+Assumptions!$B$13)^5 -> 0.50349319
A6: PV of FCF (m) | B6: =B4*B5 -> 96072.458 | C6: =C4*C5 -> 100465.77 | D6: =D4*D5 -> 95286.956 | E6: =E4*E5 -> 82935.424 | F6: =F4*F5 -> 67302.497 | G6: =SUM(B6:F6) -> 442063.11
A8: Terminal FCF (m) | G8: =F4*(1+Assumptions!$B$25) -> 137681.25
A9: Terminal value (Gordon, m) | G9: =G8/(Assumptions!$B$13 - Assumptions!$B$25) -> 1175757.9
A10: PV Terminal (Gordon, m) | G10: =G9 * F5 -> 591986.1
A11: Enterprise value (Gordon, m) | G11: =G6 + G10 -> 1034049.2
A12: Terminal value (Exit, m) | G12: =Projections!F11 * Assumptions!$B$26 -> 5048818.1
A13: PV Terminal (Exit, m) | G13: =G12 * F5 -> 2542045.5
A14: Enterprise value (Exit, m) | G14: =G6 + G13 -> 2984108.6
A16: Net cash (m) | G16: =Assumptions!B28 -> 52133
A17: Equity value (Gordon, m) | G17: =G11 + G16 -> 1086182.2
A18: Equity value (Exit, m) | G18: =G14 + G16 -> 3036241.6
A19: Shares outstanding (m) | G19: =Assumptions!B29 -> 24305
A20: Value per share (Gordon) | G20: =G17/G19 -> 44.689661
A21: Value per share (Exit) | G21: =G18/G19 -> 124.92251

Sheet Sensitivity
A1: Sensitivity Analysis
A3: WACC vs Terminal Growth (Value per share)
B4: g = 2% | C4: g = 3% | D4: g = 4%
A6: WACC = 13% | B6: =(Projections!B10/(1+0.13)^1 + Projections!C10/(1+0.13)^2 + Projections!D10/(1+0.13)^3 + Projections!E10/(1+0.13)^4 + Projections!F10/(1+0.13)^5 + (Projections!F10*(1+0.02)/(0.13-0.02))/(1+0.13)^5 + Assumptions!B28) / Assumptions!B29 -> 48.806337 | C6: =(Projections!B10/(1+0.13)^1 + Projections!C10/(1+0.13)^2 + Projections!D10/(1+0.13)^3 + Projections!E10/(1+0.13)^4 + Projections!F10/(1+0.13)^5 + (Projections!F10*(1+0.03)/(0.13-0.03))/(1+0.13)^5 + Assumptions!B28) / Assumptions!B29 -> 51.872784 | D6: =(Projections!B10/(1+0.13)^1 + Projections!C10/(1+0.13)^2 + Projections!D10/(1+0.13)^3 + Projections!E10/(1+0.13)^4 + Projections!F10/(1+0.13)^5 + (Projections!F10*(1+0.04)/(0.13-0.04))/(1+0.13)^5 + Assumptions!B28) / Assumptions!B29 -> 55.620664
A7: WACC = 14% | B7: =(Projections!B10/(1+0.14)^1 + Projections!C10/(1+0.14)^2 + Projections!D10/(1+0.14)^3 + Projections!E10/(1+0.14)^4 + Projections!F10/(1+0.14)^5 + (Projections!F10*(1+0.02)/(0.14-0.02))/(1+0.14)^5 + Assumptions!B28) / Assumptions!B29 -> 44.935521 | C7: =(Projections!B10/(1+0.14)^1 + Projections!C10/(1+0.14)^2 + Projections!D10/(1+0.14)^3 + Projections!E10/(1+0.14)^4 + Projections!F10/(1+0.14)^5 + (Projections!F10*(1+0.03)/(0.14-0.03))/(1+0.14)^5 + Assumptions!B28) / Assumptions!B29 -> 47.402404 | D7: =(Projections!B10/(1+0.14)^1 + Projections!C10/(1+0.14)^2 + Projections!D10/(1+0.14)^3 + Projections!E10/(1+0.14)^4 + Projections!F10/(1+0.14)^5 + (Projections!F10*(1+0.04)/(0.14-0.04))/(1+0.14)^5 + Assumptions!B28) / Assumptions!B29 -> 50.362664
A8: WACC = 15% | B8: =(Projections!B10/(1+0.15)^1 + Projections!C10/(1+0.15)^2 + Projections!D10/(1+0.15)^3 + Projections!E10/(1+0.15)^4 + Projections!F10/(1+0.15)^5 + (Projections!F10*(1+0.02)/(0.15-0.02))/(1+0.15)^5 + Assumptions!B28) / Assumptions!B29 -> 41.657767 | C8: =(Projections!B10/(1+0.15)^1 + Projections!C10/(1+0.15)^2 + Projections!D10/(1+0.15)^3 + Projections!E10/(1+0.15)^4 + Projections!F10/(1+0.15)^5 + (Projections!F10*(1+0.03)/(0.15-0.03))/(1+0.15)^5 + Assumptions!B28) / Assumptions!B29 -> 43.673467 | D8: =(Projections!B10/(1+0.15)^1 + Projections!C10/(1+0.15)^2 + Projections!D10/(1+0.15)^3 + Projections!E10/(1+0.15)^4 + Projections!F10/(1+0.15)^5 + (Projections!F10*(1+0.04)/(0.15-0.04))/(1+0.15)^5 + Assumptions!B28) / Assumptions!B29 -> 46.055659
A9: WACC = 16% | B9: =(Projections!B10/(1+0.16)^1 + Projections!C10/(1+0.16)^2 + Projections!D10/(1+0.16)^3 + Projections!E10/(1+0.16)^4 + Projections!F10/(1+0.16)^5 + (Projections!F10*(1+0.02)/(0.16-0.02))/(1+0.16)^5 + Assumptions!B28) / Assumptions!B29 -> 38.846136 | C9: =(Projections!B10/(1+0.16)^1 + Projections!C10/(1+0.16)^2 + Projections!D10/(1+0.16)^3 + Projections!E10/(1+0.16)^4 + Projections!F10/(1+0.16)^5 + (Projections!F10*(1+0.03)/(0.16-0.03))/(1+0.16)^5 + Assumptions!B28) / Assumptions!B29 -> 40.515068 | D9: =(Projections!B10/(1+0.16)^1 + Projections!C10/(1+0.16)^2 + Projections!D10/(1+0.16)^3 + Projections!E10/(1+0.16)^4 + Projections!F10/(1+0.16)^5 + (Projections!F10*(1+0.04)/(0.16-0.04))/(1+0.16)^5 + Assumptions!B28) / Assumptions!B29 -> 42.462155
A13: WACC vs Exit Multiple (Value per share)
B14: 30x | C14: 35x | D14: 40x
A15: WACC = 13% | B15: =(Projections!B10/(1+0.13)^1 + Projections!C10/(1+0.13)^2 + Projections!D10/(1+0.13)^3 + Projections!E10/(1+0.13)^4 + Projections!F10/(1+0.13)^5 + (Projections!F11*30)/(1+0.13)^5 + Assumptions!B28) / Assumptions!B29 -> 117.76649 | C15: =(Projections!B10/(1+0.13)^1 + Projections!C10/(1+0.13)^2 + Projections!D10/(1+0.13)^3 + Projections!E10/(1+0.13)^4 + Projections!F10/(1+0.13)^5 + (Projections!F11*35)/(1+0.13)^5 + Assumptions!B28) / Assumptions!B29 -> 133.87309 | D15: =(Projections!B10/(1+0.13)^1 + Projections!C10/(1+0.13)^2 + Projections!D10/(1+0.13)^3 + Projections!E10/(1+0.13)^4 + Projections!F10/(1+0.13)^5 + (Projections!F11*40)/(1+0.13)^5 + Assumptions!B28) / Assumptions!B29 -> 149.97969
A16: WACC = 14% | B16: =(Projections!B10/(1+0.14)^1 + Projections!C10/(1+0.14)^2 + Projections!D10/(1+0.14)^3 + Projections!E10/(1+0.14)^4 + Projections!F10/(1+0.14)^5 + (Projections!F11*30)/(1+0.14)^5 + Assumptions!B28) / Assumptions!B29 -> 113.13092 | C16: =(Projections!B10/(1+0.14)^1 + Projections!C10/(1+0.14)^2 + Projections!D10/(1+0.14)^3 + Projections!E10/(1+0.14)^4 + Projections!F10/(1+0.14)^5 + (Projections!F11*35)/(1+0.14)^5 + Assumptions!B28) / Assumptions!B29 -> 128.54337 | D16: =(Projections!B10/(1+0.14)^1 + Projections!C10/(1+0.14)^2 + Projections!D10/(1+0.14)^3 + Projections!E10/(1+0.14)^4 + Projections!F10/(1+0.14)^5 + (Projections!F11*40)/(1+0.14)^5 + Assumptions!B28) / Assumptions!B29 -> 143.95583
A17: WACC = 15% | B17: =(Projections!B10/(1+0.15)^1 + Projections!C10/(1+0.15)^2 + Projections!D10/(1+0.15)^3 + Projections!E10/(1+0.15)^4 + Projections!F10/(1+0.15)^5 + (Projections!F11*30)/(1+0.15)^5 + Assumptions!B28) / Assumptions!B29 -> 108.72711 | C17: =(Projections!B10/(1+0.15)^1 + Projections!C10/(1+0.15)^2 + Projections!D10/(1+0.15)^3 + Projections!E10/(1+0.15)^4 + Projections!F10/(1+0.15)^5 + (Projections!F11*35)/(1+0.15)^5 + Assumptions!B28) / Assumptions!B29 -> 123.48101 | D17: =(Projections!B10/(1+0.15)^1 + Projections!C10/(1+0.15)^2 + Projections!D10/(1+0.15)^3 + Projections!E10/(1+0.15)^4 + Projections!F10/(1+0.15)^5 + (Projections!F11*40)/(1+0.15)^5 + Assumptions!B28) / Assumptions!B29 -> 138.23491
A18: WACC = 16% | B18: =(Projections!B10/(1+0.16)^1 + Projections!C10/(1+0.16)^2 + Projections!D10/(1+0.16)^3 + Projections!E10/(1+0.16)^4 + Projections!F10/(1+0.16)^5 + (Projections!F11*30)/(1+0.16)^5 + Assumptions!B28) / Assumptions!B29 -> 104.54148 | C18: =(Projections!B10/(1+0.16)^1 + Projections!C10/(1+0.16)^2 + Projections!D10/(1+0.16)^3 + Projections!E10/(1+0.16)^4 + Projections!F10/(1+0.16)^5 + (Projections!F11*35)/(1+0.16)^5 + Assumptions!B28) / Assumptions!B29 -> 118.67031 | D18: =(Projections!B10/(1+0.16)^1 + Projections!C10/(1+0.16)^2 + Projections!D10/(1+0.16)^3 + Projections!E10/(1+0.16)^4 + Projections!F10/(1+0.16)^5 + (Projections!F11*40)/(1+0.16)^5 + Assumptions!B28) / Assumptions!B29 -> 132.79914

Sheet Charts
A1: Forecasted Revenue and FCF
